segobe/CLI.py
segobe/__init__.py
segobe/__main__.py
segobe/evaluator.py
segobe/plotter.py
segobe/utils.py
segobe-0.1.3.dist-info/licenses/LICENSE
segobe-0.1.3.dist-info/METADATA
segobe-0.1.3.dist-info/WHEEL
segobe-0.1.3.dist-info/entry_points.txt
segobe-0.1.3.dist-info/top_level.txt
segobe-0.1.3.dist-info/RECORD
