Metadata-Version: 2.4
Name: segobe
Version: 0.1.3
Summary: Object-Based Identification Segmentation Evaluation for cells
Author-email: Krešimir Bestak <kbestak@gmail.com>
License: MIT License
Project-URL: Homepage, https://github.com/schapirolabor/segobe
Project-URL: Issues, https://github.com/schapirolabor/segobe/issues
Keywords: segmentation,cell,metrics,evaluation
Classifier: Intended Audience :: Science/Research
Classifier: Programming Language :: Python :: 3
Classifier: License :: OSI Approved :: MIT License
Requires-Python: >=3.9
License-File: LICENSE
Requires-Dist: numpy
Requires-Dist: pandas
Requires-Dist: matplotlib
Requires-Dist: scipy
Requires-Dist: scikit-image
Requires-Dist: tifffile
Dynamic: license-file
